{"Observation_id": "6660983", "Satellite": "39430  - GOMX 1", "Station": "1729 - CSPDHQ", "Status": "Good", "Status_Message": "100", "Transmitter": "4k8 AFSK", "Frequency": "437,252,500Hz", "Mode": ["AFSK", "4800"], "Metadata": "{\"radio\": {\"name\": \"gr-satnogs\", \"version\": \"2.1.2.1\", \"parameters\": {\"soapy-rx-device\": \"driver=rtlsdr\", \"samp-rate-rx\": \"2.048e6\", \"rx-freq\": \"437252500\", \"file-path\": \"/tmp/.satnogs/data/receiving_satnogs_6660983_2022-10-27T22-11-22.out\", \"waterfall-file-path\": \"/tmp/.satnogs/data/receiving_waterfall_6660983_2022-10-27T22-11-22.dat\", \"decoded-data-file-path\": \"/tmp/.satnogs/data/data_6660983\", \"doppler-correction-per-sec\": null, \"lo-offset\": null, \"ppm\": null, \"rigctl-port\": \"4532\", \"gain-mode\": \"Overall\", \"gain\": \"38.2\", \"antenna\": \"RX\", \"dev-args\": null, \"stream-args\": null, \"tune-args\": null, \"other-settings\": null, \"dc-removal\": null, \"bb-freq\": null, \"bw\": null, \"enable-iq-dump\": \"0\", \"iq-file-path\": null, \"wpm\": null, \"baudrate\": null, \"framing\": null}}, \"latitude\": 45.239, \"longitude\": 19.809, \"elevation\": 85, \"frequency\": 437252500}", "Downloads": {"audio": "https://network-satnogs.freetls.fastly.net/media/data_obs/2022/10/27/22/6660983/satnogs_6660983_2022-10-27T22-11-22.ogg", "waterfall": "https://s3.eu-central-1.wasabisys.com/satnogs-network/data_obs/2022/10/27/22/6660983/waterfall_6660983_2022-10-27T22-11-22.png", "waterfall_hash_name": "./data/observations/waterfalls/17d0f5faa0ebcef12091b4cc8b131cbafd17fb881c4ecd0547ba55062138e729", "waterfall_shape": [1542, 623]}, "Waterfall_Status": "Vetted With Signal on 2022-10-27 23:58:16 by Miloslav YT2CQ Miskar "}