{"Observation_id": "6661476", "Satellite": "53108  - TRISAT-R", "Station": "1466 - PE0SAT-12", "Status": "Bad", "Status_Message": "-100", "Transmitter": "Mode U -  GFSK 1kbps TLM", "Frequency": "435,612,500Hz", "Mode": ["GFSK", "1000"], "Metadata": "{\"radio\": {\"name\": \"gr-satnogs\", \"version\": \"v2.3-compat-xxx-v2.3.3.0\", \"parameters\": {\"soapy-rx-device\": \"driver=airspy,serial=466c64c8306b65c7,biastee=true\", \"samp-rate-rx\": \"2.5e6\", \"rx-freq\": \"435612500\", \"file-path\": \"/tmp/.satnogs/data/receiving_satnogs_6661476_2022-10-27T03-33-35.out\", \"waterfall-file-path\": \"/tmp/.satnogs/data/receiving_waterfall_6661476_2022-10-27T03-33-35.dat\", \"decoded-data-file-path\": \"/tmp/.satnogs/data/data_6661476\", \"doppler-correction-per-sec\": null, \"lo-offset\": null, \"ppm\": null, \"rigctl-port\": \"4535\", \"gain-mode\": \"Settings Field\", \"gain\": null, \"antenna\": \"RX\", \"dev-args\": null, \"stream-args\": null, \"tune-args\": null, \"other-settings\": \"LNA=12,MIX=8,VGA=11\", \"dc-removal\": null, \"bb-freq\": null, \"bw\": null, \"enable-iq-dump\": \"1\", \"iq-file-path\": \"/home/lab/1466/data/iq/iq_1466.raw\", \"udp-dump-host\": \"127.0.0.1\", \"udp-dump-port\": 51466, \"wpm\": null, \"baudrate\": \"1000\", \"framing\": \"ax25\"}}, \"latitude\": 51.721, \"longitude\": 5.03, \"elevation\": 5, \"frequency\": 435612500}", "Downloads": {"audio": "https://network-satnogs.freetls.fastly.net/media/data_obs/2022/10/27/3/6661476/satnogs_6661476_2022-10-27T03-33-35.ogg", "waterfall": "https://s3.eu-central-1.wasabisys.com/satnogs-network/data_obs/2022/10/27/3/6661476/waterfall_6661476_2022-10-27T03-33-35.png", "waterfall_hash_name": "./data/observations/waterfalls/d0c3bf113211d12de5ad2e765716c6e725c3659471105f5b63d610249fb50305", "waterfall_shape": [1542, 623]}, "Waterfall_Status": "Vetted Without Signal on 2022-10-27 05:06:51 by PE0SAT "}