{"Observation_id": "6661722", "Satellite": "44109  - M6P", "Station": "901 - VE2WI - UHF", "Status": "Bad", "Status_Message": "-100", "Transmitter": "FSK9k6", "Frequency": "437,265,000Hz", "Mode": ["FSK", "9600"], "Metadata": "{\"latitude\": 45.4198416667, \"elevation\": 15.0, \"frequency\": 437265000, \"radio\": {\"bb_gain\": null, \"version\": \"1.5.1.0\", \"name\": \"gr-satnogs\", \"antenna\": \"VHF vertical\", \"ppm_error\": null, \"if_gain\": null, \"rx_device\": \"rtlsdr\", \"rf_gain\": \"38\"}, \"longitude\": -73.4649944444}", "Downloads": {"audio": "https://network-satnogs.freetls.fastly.net/media/data_obs/2022/10/26/16/6661722/satnogs_6661722_2022-10-26T16-39-20.ogg", "waterfall": "https://s3.eu-central-1.wasabisys.com/satnogs-network/data_obs/2022/10/26/16/6661722/waterfall_6661722_2022-10-26T16-39-20.png", "waterfall_hash_name": "./data/observations/waterfalls/f473c43af4e93129710c82b73c02f50cc9ca18a838ba20c7a2273c478f1bce00", "waterfall_shape": [1542, 623]}, "Waterfall_Status": "Vetted Without Signal on 2022-10-28 01:55:06 by Laurent Beaudet "}