{"Observation_id": "6663949", "Satellite": "40069  - METEOR M-2", "Station": "2334 - M7CBR - VHF Turnstile", "Status": "Good", "Status_Message": "100", "Transmitter": "LRPT 1", "Frequency": "137,100,000Hz", "Mode": ["LRPT", "72000"], "Metadata": "{\"radio\": {\"name\": \"gr-satnogs\", \"version\": \"v2.3-compat-xxx-v2.3.1.0\", \"parameters\": {\"soapy-rx-device\": \"driver=rtlsdr\", \"samp-rate-rx\": \"2.048e6\", \"rx-freq\": \"137100000\", \"file-path\": \"/tmp/.satnogs/data/receiving_satnogs_6663949_2022-10-27T06-08-53.out\", \"waterfall-file-path\": \"/tmp/.satnogs/data/receiving_waterfall_6663949_2022-10-27T06-08-53.dat\", \"decoded-data-file-path\": \"/tmp/.satnogs/data/data_6663949\", \"doppler-correction-per-sec\": null, \"lo-offset\": null, \"ppm\": null, \"rigctl-port\": \"4532\", \"gain-mode\": \"Overall\", \"gain\": \"33.8\", \"antenna\": \"RX\", \"dev-args\": null, \"stream-args\": null, \"tune-args\": null, \"other-settings\": null, \"dc-removal\": null, \"bb-freq\": null, \"bw\": null, \"enable-iq-dump\": \"0\", \"iq-file-path\": null, \"udp-dump-host\": null, \"udp-dump-port\": 57356, \"wpm\": null, \"baudrate\": null, \"framing\": null}}, \"latitude\": 53.728, \"longitude\": -2.356, \"elevation\": 223, \"frequency\": 137100000}", "Downloads": {"audio": null, "waterfall": "https://s3.eu-central-1.wasabisys.com/satnogs-network/data_obs/2022/10/27/6/6663949/waterfall_6663949_2022-10-27T06-08-53.png", "waterfall_hash_name": "./data/observations/waterfalls/850fffeb65f49c55caf9ae345d09acd308ae670df58e3a1a500eb0a3b09e3a79", "waterfall_shape": [1542, 623]}, "Waterfall_Status": "Vetted With Signal on 2022-10-27 07:37:42 by Cameron Boyer (M7CBR) "}