{"Observation_id": "6664612", "Satellite": "52950  - CTIM", "Station": "1775 - Vi3w Roy4l", "Status": "Bad", "Status_Message": "-100", "Transmitter": "Mode U/U - GFSK 9k6 AX.25 G3RUH (SpaceQuest TRX-U)", "Frequency": "437,250,000Hz", "Mode": ["GFSK", "9600"], "Metadata": "{\"radio\": {\"name\": \"gr-satnogs\", \"version\": \"v2.2-compat-xxx-v2.2.0.0\", \"parameters\": {\"soapy-rx-device\": \"driver=rtlsdr\", \"samp-rate-rx\": \"2.048e6\", \"rx-freq\": \"437250000\", \"file-path\": \"/tmp/.satnogs/data/receiving_satnogs_6664612_2022-10-27T21-05-55.out\", \"waterfall-file-path\": \"/tmp/.satnogs/data/receiving_waterfall_6664612_2022-10-27T21-05-55.dat\", \"decoded-data-file-path\": \"/tmp/.satnogs/data/data_6664612\", \"doppler-correction-per-sec\": null, \"lo-offset\": null, \"ppm\": null, \"rigctl-port\": \"4532\", \"gain-mode\": \"Overall\", \"gain\": \"43.9\", \"antenna\": \"RX\", \"dev-args\": null, \"stream-args\": null, \"tune-args\": null, \"other-settings\": null, \"dc-removal\": null, \"bb-freq\": null, \"bw\": null, \"enable-iq-dump\": \"0\", \"iq-file-path\": null, \"wpm\": null, \"baudrate\": \"9600\", \"framing\": \"ax25\"}}, \"latitude\": 48.454598, \"longitude\": -123.441462, \"elevation\": 9, \"frequency\": 437250000}", "Downloads": {"audio": "https://network-satnogs.freetls.fastly.net/media/data_obs/2022/10/27/21/6664612/satnogs_6664612_2022-10-27T21-05-55.ogg", "waterfall": "https://s3.eu-central-1.wasabisys.com/satnogs-network/data_obs/2022/10/27/21/6664612/waterfall_6664612_2022-10-27T21-05-55.png", "waterfall_hash_name": "./data/observations/waterfalls/fc42368a0eed24b65ffbd0d52b91390631103fece0cc318cfb0b59123d5f9abe", "waterfall_shape": [1542, 623]}, "Waterfall_Status": "Vetted Without Signal on 2022-10-28 05:38:48 by Vi3w Roy4l "}