{"Observation_id": "6664105", "Satellite": "44103  - AISTECHSAT-3", "Station": "2302 - AB3ZW", "Status": "Good", "Status_Message": "100", "Transmitter": "Mode U - GFSK9k6", "Frequency": "436,730,000Hz", "Mode": ["FSK AX.100 Mode 5", "9600"], "Metadata": "{\"radio\": {\"name\": \"gr-satnogs\", \"version\": \"v2.3-compat-xxx-v2.3.3.0\", \"parameters\": {\"soapy-rx-device\": \"driver=rtlsdr\", \"samp-rate-rx\": \"2.048e06\", \"rx-freq\": \"436730000\", \"file-path\": \"/tmp/.satnogs/data/receiving_satnogs_6664105_2022-10-27T01-46-15.out\", \"waterfall-file-path\": \"/tmp/.satnogs/data/receiving_waterfall_6664105_2022-10-27T01-46-15.dat\", \"decoded-data-file-path\": \"/tmp/.satnogs/data/data_6664105\", \"doppler-correction-per-sec\": null, \"lo-offset\": null, \"ppm\": \"46\", \"rigctl-port\": \"4532\", \"gain-mode\": \"Overall\", \"gain\": \"29.7\", \"antenna\": \"RX\", \"dev-args\": null, \"stream-args\": null, \"tune-args\": null, \"other-settings\": null, \"dc-removal\": null, \"bb-freq\": null, \"bw\": null, \"enable-iq-dump\": \"0\", \"iq-file-path\": null, \"udp-dump-host\": null, \"udp-dump-port\": 57356, \"wpm\": null, \"baudrate\": \"9600\", \"framing\": \"ax100_mode5\"}}, \"latitude\": 39.472, \"longitude\": -76.332, \"elevation\": 8, \"frequency\": 436730000}", "Downloads": {"audio": "https://network-satnogs.freetls.fastly.net/media/data_obs/2022/10/27/1/6664105/satnogs_6664105_2022-10-27T01-46-15.ogg", "waterfall": "https://s3.eu-central-1.wasabisys.com/satnogs-network/data_obs/2022/10/27/1/6664105/waterfall_6664105_2022-10-27T01-46-15.png", "waterfall_hash_name": "./data/observations/waterfalls/42bf9dec0de03a4a4bc04bc26a61d9091f96e4f924f4e38f7f8d889d62615804", "waterfall_shape": [1542, 623]}, "Waterfall_Status": "Vetted With Signal on 2022-10-27 13:04:15 by Ricardo Trujillo "}