{"Observation_id": "6666659", "Satellite": "43793  - CSIM-FD", "Station": "1675 - MAUSyagi", "Status": "Good", "Status_Message": "100", "Transmitter": "GFSK9k6 TLM", "Frequency": "437,250,000Hz", "Mode": ["GFSK", "9600"], "Metadata": "{\"radio\": {\"name\": \"gr-satnogs\", \"version\": \"v2.3-compat-xxx-v2.3.2.0\", \"parameters\": {\"soapy-rx-device\": \"driver=rtlsdr\", \"samp-rate-rx\": \"2.048e6\", \"rx-freq\": \"437250000\", \"file-path\": \"/data1/satnogs/1675/data/receiving_satnogs_6666659_2022-10-28T14-19-06.out\", \"waterfall-file-path\": \"/data1/satnogs/1675/data/receiving_waterfall_6666659_2022-10-28T14-19-06.dat\", \"decoded-data-file-path\": \"/data1/satnogs/1675/data/data_6666659\", \"doppler-correction-per-sec\": null, \"lo-offset\": null, \"ppm\": null, \"rigctl-port\": \"4532\", \"gain-mode\": \"Overall\", \"gain\": \"44.5\", \"antenna\": \"RX\", \"dev-args\": null, \"stream-args\": null, \"tune-args\": null, \"other-settings\": null, \"dc-removal\": null, \"bb-freq\": null, \"bw\": null, \"enable-iq-dump\": \"1\", \"iq-file-path\": \"/data1/satnogs/1675/data/iq.dat\", \"udp-dump-host\": \"127.0.0.1\", \"udp-dump-port\": 57356, \"wpm\": null, \"baudrate\": \"9600\", \"framing\": \"ax25\"}}, \"latitude\": 42.288, \"longitude\": -73.33, \"elevation\": 300, \"frequency\": 437250000}", "Downloads": {"audio": "https://network-satnogs.freetls.fastly.net/media/data_obs/2022/10/28/14/6666659/satnogs_6666659_2022-10-28T14-19-06.ogg", "waterfall": "https://s3.eu-central-1.wasabisys.com/satnogs-network/data_obs/2022/10/28/14/6666659/waterfall_6666659_2022-10-28T14-19-06.png", "waterfall_hash_name": "./data/observations/waterfalls/c3fd3fb0e1e0eaf8897d67a3cd2d299aace56a8a91892392280ef31f025e10ba", "waterfall_shape": [1542, 623]}, "Waterfall_Status": "Vetted With Signal on 2022-10-28 14:54:42 by MAUSyagi "}