{"Observation_id": "6666053", "Satellite": "46276  - UPMSat 2", "Station": "2302 - AB3ZW", "Status": "Good", "Status_Message": "100", "Transmitter": "TLM", "Frequency": "437,405,000Hz", "Mode": ["FSK", "1200"], "Metadata": "{\"radio\": {\"name\": \"gr-satnogs\", \"version\": \"v2.3-compat-xxx-v2.3.3.0\", \"parameters\": {\"soapy-rx-device\": \"driver=rtlsdr\", \"samp-rate-rx\": \"2.048e06\", \"rx-freq\": \"437405000\", \"file-path\": \"/tmp/.satnogs/data/receiving_satnogs_6666053_2022-10-27T15-18-08.out\", \"waterfall-file-path\": \"/tmp/.satnogs/data/receiving_waterfall_6666053_2022-10-27T15-18-08.dat\", \"decoded-data-file-path\": \"/tmp/.satnogs/data/data_6666053\", \"doppler-correction-per-sec\": null, \"lo-offset\": null, \"ppm\": \"46\", \"rigctl-port\": \"4532\", \"gain-mode\": \"Overall\", \"gain\": \"29.7\", \"antenna\": \"RX\", \"dev-args\": null, \"stream-args\": null, \"tune-args\": null, \"other-settings\": null, \"dc-removal\": null, \"bb-freq\": null, \"bw\": null, \"enable-iq-dump\": \"0\", \"iq-file-path\": null, \"udp-dump-host\": null, \"udp-dump-port\": 57356, \"wpm\": null, \"baudrate\": \"1200\", \"framing\": \"ax25\"}}, \"latitude\": 39.472, \"longitude\": -76.332, \"elevation\": 8, \"frequency\": 437405000}", "Downloads": {"audio": "https://network-satnogs.freetls.fastly.net/media/data_obs/2022/10/27/15/6666053/satnogs_6666053_2022-10-27T15-18-08.ogg", "waterfall": "https://s3.eu-central-1.wasabisys.com/satnogs-network/data_obs/2022/10/27/15/6666053/waterfall_6666053_2022-10-27T15-18-08.png", "waterfall_hash_name": "./data/observations/waterfalls/6c056d4e8e2c5cb49a66af5960fc878e4558c29d58fbaeacd84224db8624eff1", "waterfall_shape": [1542, 623]}, "Waterfall_Status": "Vetted With Signal on 2022-10-27 17:06:31 by Ricardo Trujillo "}