{"Observation_id": "6667975", "Satellite": "35935  - ITUPSAT 1", "Station": "901 - VE2WI - UHF", "Status": "Good", "Status_Message": "100", "Transmitter": "GMSK Telemetry Drifted", "Frequency": "437,320,000Hz", "Mode": ["GFSK", "19200"], "Metadata": "{\"latitude\": 45.4198416667, \"elevation\": 15.0, \"frequency\": 437320000, \"radio\": {\"bb_gain\": null, \"version\": \"1.5.1.0\", \"name\": \"gr-satnogs\", \"antenna\": \"VHF vertical\", \"ppm_error\": null, \"if_gain\": null, \"rx_device\": \"rtlsdr\", \"rf_gain\": \"38\"}, \"longitude\": -73.4649944444}", "Downloads": {"audio": "https://network-satnogs.freetls.fastly.net/media/data_obs/2022/10/28/1/6667975/satnogs_6667975_2022-10-28T01-38-29.ogg", "waterfall": "https://s3.eu-central-1.wasabisys.com/satnogs-network/data_obs/2022/10/28/1/6667975/waterfall_6667975_2022-10-28T01-38-29.png", "waterfall_hash_name": "./data/observations/waterfalls/287e7e37ff1f16b8e140477f8dc998ea073c08d0f1c41237b1437c5227aec0f4", "waterfall_shape": [1542, 623]}, "Waterfall_Status": "Vetted With Signal on 2022-10-28 01:57:29 by Laurent Beaudet "}