{"Observation_id": "6667768", "Satellite": "47960  - Orbicraft-Zorkiy", "Station": "91 - M0EYT / 2E0NOG", "Status": "Good", "Status_Message": "100", "Transmitter": "Mode U - GMSK9k6 USP FEC A", "Frequency": "437,850,000Hz", "Mode": ["GMSK", "9600"], "Metadata": "{\"radio\": {\"name\": \"gr-satnogs\", \"version\": \"v2.3-compat-xxx-v2.3.3.0\", \"parameters\": {\"soapy-rx-device\": \"driver=airspy\", \"samp-rate-rx\": \"2.5e6\", \"rx-freq\": \"437850000\", \"file-path\": \"/tmp/.satnogs/data/receiving_satnogs_6667768_2022-10-28T09-50-03.out\", \"waterfall-file-path\": \"/tmp/.satnogs/data/receiving_waterfall_6667768_2022-10-28T09-50-03.dat\", \"decoded-data-file-path\": \"/tmp/.satnogs/data/data_6667768\", \"doppler-correction-per-sec\": null, \"lo-offset\": null, \"ppm\": \"0\", \"rigctl-port\": \"4532\", \"gain-mode\": \"Settings Field\", \"gain\": \"43\", \"antenna\": \"RX\", \"dev-args\": null, \"stream-args\": null, \"tune-args\": null, \"other-settings\": \"LNA=13,MIX=9,VGA=11\\\"\\\"\", \"dc-removal\": null, \"bb-freq\": null, \"bw\": null, \"enable-iq-dump\": \"1\", \"iq-file-path\": \"/datadrive/meteor/new_iq/last_obs.iq\", \"udp-dump-host\": null, \"udp-dump-port\": 57356, \"wpm\": null, \"baudrate\": \"9600\", \"framing\": \"ax25\"}}, \"latitude\": 50.77, \"longitude\": -2.02, \"elevation\": 60, \"frequency\": 437850000}", "Downloads": {"audio": "https://network-satnogs.freetls.fastly.net/media/data_obs/2022/10/28/9/6667768/satnogs_6667768_2022-10-28T09-50-03.ogg", "waterfall": "https://s3.eu-central-1.wasabisys.com/satnogs-network/data_obs/2022/10/28/9/6667768/waterfall_6667768_2022-10-28T09-50-03.png", "waterfall_hash_name": "./data/observations/waterfalls/d38cb437d491f7208086a4358583d64265d7b2223d626321e3e78c9d468dd93f", "waterfall_shape": [1542, 623]}, "Waterfall_Status": "Vetted With Signal on 2022-10-28 16:41:32 by UHF Satcom "}