{"Observation_id": "6670111", "Satellite": "50998  - Tevel-5", "Station": "2051 - MAUSyagi", "Status": "Good", "Status_Message": "100", "Transmitter": "Mode U - BPSK9k6 G3RUH", "Frequency": "436,400,000Hz", "Mode": ["BPSK", "9600"], "Metadata": "{\"radio\": {\"name\": \"gr-satnogs\", \"version\": \"v2.3-compat-xxx-v2.3.3.0\", \"parameters\": {\"soapy-rx-device\": \"driver=rtlsdr\", \"samp-rate-rx\": \"2.048e6\", \"rx-freq\": \"436400000\", \"file-path\": \"/data/satnogs/data/receiving_satnogs_6670111_2022-10-28T14-50-17.out\", \"waterfall-file-path\": \"/data/satnogs/data/receiving_waterfall_6670111_2022-10-28T14-50-17.dat\", \"decoded-data-file-path\": \"/data/satnogs/data/data_6670111\", \"doppler-correction-per-sec\": null, \"lo-offset\": null, \"ppm\": null, \"rigctl-port\": \"4532\", \"gain-mode\": \"Overall\", \"gain\": \"42.1\", \"antenna\": \"RX\", \"dev-args\": null, \"stream-args\": null, \"tune-args\": null, \"other-settings\": null, \"dc-removal\": null, \"bb-freq\": null, \"bw\": null, \"enable-iq-dump\": \"1\", \"iq-file-path\": \"/data/satnogs/data/iq.dat\", \"udp-dump-host\": \"127.0.0.1\", \"udp-dump-port\": 57356, \"wpm\": null, \"baudrate\": \"9600\", \"framing\": \"ax25\"}}, \"latitude\": 42.288, \"longitude\": -73.33, \"elevation\": 300, \"frequency\": 436400000}", "Downloads": {"audio": "https://network-satnogs.freetls.fastly.net/media/data_obs/2022/10/28/14/6670111/satnogs_6670111_2022-10-28T14-50-17.ogg", "waterfall": "https://s3.eu-central-1.wasabisys.com/satnogs-network/data_obs/2022/10/28/14/6670111/waterfall_6670111_2022-10-28T14-50-17.png", "waterfall_hash_name": "./data/observations/waterfalls/695f6662e4c2786752847a3cec966fd5b8a1eda770ae8bcc2d891a0440b0d9a4", "waterfall_shape": [1542, 623]}, "Waterfall_Status": "Vetted With Signal on 2022-10-28 14:55:16 by MAUSyagi "}